onesecmail_api/__init__.py
onesecmail_api/onesecmail_api.py
onesecmail_api-0.1.0.dist-info/METADATA
onesecmail_api-0.1.0.dist-info/WHEEL
onesecmail_api-0.1.0.dist-info/top_level.txt
onesecmail_api-0.1.0.dist-info/RECORD
