Metadata-Version: 2.1
Name: onesecmail-api
Version: 0.1.0
Summary: 1secmail unofficial API, supporting random email generation, fetching messages and downloading attachments
Home-page: https://github.com/st1vms/onesecmail-api
Author: st1vms
Author-email: stefano.maria.salvatore@gmail.com
Classifier: Programming Language :: Python :: 3.9
Classifier: License :: OSI Approved :: MIT License
Classifier: Operating System :: OS Independent
Requires-Python: >=3.9
Requires-Dist: requests
